cvlive/__init__.py
cvlive/processor.py
cvlive-0.1.3.dist-info/LICENSE
cvlive-0.1.3.dist-info/METADATA
cvlive-0.1.3.dist-info/WHEEL
cvlive-0.1.3.dist-info/top_level.txt
cvlive-0.1.3.dist-info/RECORD
