Metadata-Version: 2.1
Name: cvlive
Version: 0.1.3
Summary: A multithreaded live image processor in Python running OpenCV
Home-page: https://github.com/Emilostuff/cvlive
Author: Emil Skydsgaard
Author-email: emilostuff@gmail.com
Keywords: OpenCV,image,processing,computer,vision,demo,multithreaded
Classifier: Development Status :: 3 - Alpha
Classifier: Intended Audience :: Education
Classifier: License :: OSI Approved :: MIT License
Classifier: Programming Language :: Python :: 3
Classifier: Topic :: Scientific/Engineering :: Image Processing
Requires-Python: >=3.8, <4
License-File: LICENSE
Requires-Dist: opencv-python
